studyclient/__init__.py
studyclient/connection.py
studyclient/core.py
studyclient/drivers.py
studyclient/exceptions.py
studygovernor_client-0.4.0.dist-info/LICENSE
studygovernor_client-0.4.0.dist-info/METADATA
studygovernor_client-0.4.0.dist-info/WHEEL
studygovernor_client-0.4.0.dist-info/entry_points.txt
studygovernor_client-0.4.0.dist-info/top_level.txt
studygovernor_client-0.4.0.dist-info/RECORD
